README.md
setup.py
camelsplit/__init__.py
camelsplit/camelsplit.py
camelsplit.egg-info/PKG-INFO
camelsplit.egg-info/SOURCES.txt
camelsplit.egg-info/dependency_links.txt
camelsplit.egg-info/top_level.txt
camelsplit/tests/__init__.py
camelsplit/tests/test_basic.py