Metadata-Version: 2.1
Name: camelsplit
Version: 1.0.1
Summary: Camel case aware word splitting.
Home-page: https://github.com/flopp/camelsplit
Author: Florian Pigorsch
Author-email: mail@florian-pigorsch.de
License: UNKNOWN
Platform: UNKNOWN
Classifier: Programming Language :: Python :: 2
Classifier: Programming Language :: Python :: 3
Classifier: License :: OSI Approved :: MIT License
Classifier: Operating System :: OS Independent
